rpip.py
rpip-1.1.dist-info/METADATA
rpip-1.1.dist-info/WHEEL
rpip-1.1.dist-info/entry_points.txt
rpip-1.1.dist-info/top_level.txt
rpip-1.1.dist-info/RECORD
