Metadata-Version: 2.1
Name: rpip
Version: 1.1
Summary: Utility to recursively install requirements using pip
Home-page: https://git.whoi.edu/acomms/rpip/
Author: whoi
Author-email: egallimore@whoi.edu
Classifier: Programming Language :: Python :: 3
Classifier: License :: OSI Approved :: MIT License
Classifier: Operating System :: OS Independent
Requires-Python: >=3.6
